mimeiapify/__init__.py
mimeiapify/airtable/__init__.py
mimeiapify/airtable/airtable.py
mimeiapify/airtable/airtable_async.py
mimeiapify/symphony_ai/__init__.py
mimeiapify/symphony_ai/openai_utils/__init__.py
mimeiapify/symphony_ai/redis/README.md
mimeiapify/symphony_ai/redis/__init__.py
mimeiapify/symphony_ai/redis/context.py
mimeiapify/symphony_ai/redis/ops.py
mimeiapify/symphony_ai/redis/redis_client.py
mimeiapify/symphony_ai/redis/listeners/README.md
mimeiapify/symphony_ai/redis/listeners/__init__.py
mimeiapify/symphony_ai/redis/listeners/example_handlers.py
mimeiapify/symphony_ai/redis/listeners/expiry_listener.py
mimeiapify/symphony_ai/redis/listeners/handler_registry.py
mimeiapify/symphony_ai/redis/listeners/test_integration.py
mimeiapify/symphony_ai/redis/redis_handler/__init__.py
mimeiapify/symphony_ai/redis/redis_handler/batch.py
mimeiapify/symphony_ai/redis/redis_handler/generic.py
mimeiapify/symphony_ai/redis/redis_handler/shared_state.py
mimeiapify/symphony_ai/redis/redis_handler/state_handler.py
mimeiapify/symphony_ai/redis/redis_handler/table.py
mimeiapify/symphony_ai/redis/redis_handler/trigger.py
mimeiapify/symphony_ai/redis/redis_handler/user.py
mimeiapify/symphony_ai/redis/redis_handler/utils/__init__.py
mimeiapify/symphony_ai/redis/redis_handler/utils/key_factory.py
mimeiapify/symphony_ai/redis/redis_handler/utils/serde.py
mimeiapify/symphony_ai/redis/redis_handler/utils/tenant_cache.py
mimeiapify/symphony_ai/symphony_concurrency/README.md
mimeiapify/symphony_ai/symphony_concurrency/__init__.py
mimeiapify/symphony_ai/symphony_concurrency/globals.py
mimeiapify/symphony_ai/symphony_concurrency/pubsub/__init__.py
mimeiapify/symphony_ai/symphony_concurrency/pubsub/pubsub_client.py
mimeiapify/symphony_ai/symphony_concurrency/tools/__init__.py
mimeiapify/symphony_ai/symphony_concurrency/tools/async_tool.py
mimeiapify/symphony_ai/symphony_concurrency/tools/user_threads.py
mimeiapify/utils/__init__.py
mimeiapify/utils/helper_functions.py
mimeiapify-1.4.3.dist-info/METADATA
mimeiapify-1.4.3.dist-info/WHEEL
mimeiapify-1.4.3.dist-info/licenses/LICENSE
mimeiapify-1.4.3.dist-info/RECORD
