Metadata-Version: 2.4
Name: mimeiapify
Version: 1.4.3
Summary: A utility library for API interactions including Wompi payments and Airtable
Project-URL: Homepage, https://github.com/sashanclrp/mimeiapify
Project-URL: Issues, https://github.com/sashanclrp/mimeiapify/issues
Project-URL: Repository, https://github.com/sashanclrp/mimeiapify.git
Author-email: Sasha Nicolai Canal <sasha@candyflip.co>
License: MIT License
License-File: LICENSE
Classifier: Development Status :: 4 - Beta
Classifier: Intended Audience :: Developers
Classifier: License :: OSI Approved :: MIT License
Classifier: Operating System :: OS Independent
Classifier: Programming Language :: Python :: 3
Classifier: Topic :: Software Development :: Libraries :: Python Modules
Requires-Python: >=3.12
Requires-Dist: agency-swarm>=0.6.1
Requires-Dist: aiohttp>=3.8.0
Requires-Dist: anyio>=4.9.0
Requires-Dist: pandas>=1.3.0
Requires-Dist: pydantic>=2.10.6
Requires-Dist: redis>=6.2.0
Requires-Dist: requests>=2.25.0
Requires-Dist: rich>=13.9.4
Provides-Extra: dev
Requires-Dist: black>=22.0.0; extra == 'dev'
Requires-Dist: mypy>=1.0.0; extra == 'dev'
Requires-Dist: pytest-asyncio>=0.21.0; extra == 'dev'
Requires-Dist: pytest>=7.0.0; extra == 'dev'
Requires-Dist: ruff>=0.1.0; extra == 'dev'
